{
  "description": "In this talk, I will give an overview of the ONNX (https://onnx.ai) and ONNX Runtime (https://onnxruntime.ai) projects. I will focus on the motivation, the architecture, the adoption, the lessons, and the future roadmap of ONNX and ONNX Runtime. I will discuss the work we are collaborating with OctoML on integrating TVM and ONNX Runtime.\n\n",
  "language": "eng",
  "recorded": "2021-12-17",
  "speakers": [
    "Manash Goswami (Microsoft)", 
    "Ganesan Ramalingam (Microsoft)"
  ],
  "thumbnail_url": "https://i.ytimg.com/vi/o2djVyvDmPQ/hqdefault.jpg",
  "title": "ONNX, ONNX Runtime, and TVM",
  "videos": [
    {
      "type": "youtube",
      "url": "https://youtu.be/FSwuk_9xxrc"
    }
  ]
}
